<?xml version="1.0" encoding="UTF-8" standalone="yes"?>
<persistence xmlns="https://jakarta.ee/xml/ns/persistence"
             xmlns:xsi="http://www.w3.org/2001/XMLSchema-instance"
             xsi:schemaLocation="https://jakarta.ee/xml/ns/persistence https://jakarta.ee/xml/ns/persistence/persistence_3_0.xsd"
             version="3.0">
  <persistence-unit name="default">

      <class>Entity.Admins</class>
      <class>Entity.Aeroport</class>
      <class>Entity.Clients</class>
      <class>Entity.Escales</class>
      <class>Entity.Extras</class>
      <class>Entity.ExtrasReservation</class>
      <class>Entity.Paiement</class>
      <class>Entity.Reservations</class>
      <class>Entity.Societe</class>
      <class>Entity.Vols</class>
      <class>Entity.VolsReservation</class>
      <properties>
          <property name="toplink.jdbc.url" value="jdbc:postgresql://localhost:5432/airafrikaapp"/>
          <property name="toplink.jdbc.driver" value="org.postgresql.Driver"/>
          <property name="toplink.jdbc.user" value="postgres"/>
          <property name="toplink.jdbc.password" value="najoua"/>
          <property name="hibernate.connection.url" value="jdbc:postgresql://localhost:5432/airafrikaapp"/>
          <property name="hibernate.connection.driver_class" value="org.postgresql.Driver"/>
          <property name="hibernate.connection.username" value="postgres"/>
          <property name="hibernate.connection.password" value="najoua"/>
          <property name="openjpa.ConnectionURL" value="jdbc:postgresql://localhost:5432/airafrikaapp"/>
          <property name="openjpa.ConnectionDriverName" value="org.postgresql.Driver"/>
          <property name="openjpa.ConnectionUserName" value="postgres"/>
          <property name="openjpa.ConnectionPassword" value="najoua"/>
          <property name="eclipselink.jdbc.url" value="jdbc:postgresql://localhost:5432/airafrikaapp"/>
          <property name="eclipselink.jdbc.driver" value="org.postgresql.Driver"/>
          <property name="eclipselink.jdbc.user" value="postgres"/>
          <property name="eclipselink.jdbc.password" value="najoua"/>
          <property name="hibernate.show_sql" value="true"/>
      </properties>
  </persistence-unit>
</persistence>
